{
  "id": "light",
  "displayName": "Air",
  "themeDisplayColor": "#f5f5f5",
  "iconPath": "/assets/128/light-alt.png",

  
  "surface": {
    "base": "#f5f5f5",
    "elevated": "#e8e8e8",
    "overlay": "#e8e8e8",
    "code": "#00bfff",
    "toggle": "#cccccc"
  },
  "text": {
    "primary": "#1a1a1a",
    "secondary": "#555555",
    "muted": "#808080",
    "accent": "#00bfff",
    "code": "#ffffff"
  },
  "border": {
    "default": "#dedede",
    "active": "#00bfff",
    "subtle": "#d0d0d0"
  },
  "effects": {
    "overlay": {
      "opacity": 0.85,
      "blur": "12px"
    },
    "fade": "#f5f5f5"
  },
  "tabSelector": {
    "idle": {
      "color": "#808080"
    },
    "hover": {
      "color": "#000000",
      "background": "00bfff",
      "opacity": 0.0
    },
    "active": {
      "color": "#ffffff",
      "background": "#00bfff"
    }
  }
}
